{
  "hero": {
    "cta": {
      "primary": "Our Capabilities",
      "secondary": "Contact Us"
    },
    "type": "image",
    "title": "About Jyoti Precision",
    "enabled": true,
    "subtitle": "Engineering Excellence in Precision Manufacturing Since 2005",
    "description": "Jyoti Precision has been a leading manufacturer of high-quality precision components for the automobile and pneumatic sectors. With over 100 specialized part types, we deliver innovative solutions that drive industrial performance and reliability.",
    "backgroundImage": "https://images.unsplash.com/photo-1581579186913-45ac24ed53d2"
  },
  "meta": {
    "title": "Jyoti Precision - Precision Manufacturing Excellence",
    "description": "Leading precision component manufacturer specializing in automotive and pneumatic sector parts with advanced manufacturing capabilities since 2005."
  },
  "sections": {
    "cta": {
      "type": "cta",
      "title": "Partner with Industry Leaders",
      "enabled": true,
      "subtitle": "Transform Your Manufacturing Needs with Precision Engineering",
      "primaryCTA": {
        "text": "Get Quote",
        "action": "/contact"
      },
      "secondaryCTA": {
        "text": "Explore Services",
        "action": "/services"
      }
    },
    "awards": {
      "type": "awards",
      "items": [
        {
          "id": "manufacturing-excellence",
          "year": "2022",
          "title": "Manufacturing Excellence Award",
          "authority": "Indian Manufacturing Association",
          "description": "Recognized for outstanding precision engineering and technological innovation in component manufacturing"
        },
        {
          "id": "quality-leadership",
          "year": "2021",
          "title": "Quality Leadership Award",
          "authority": "National Quality Council",
          "description": "Acknowledged for consistent high-quality manufacturing standards and process optimization"
        }
      ],
      "title": "Awards & Recognition",
      "enabled": true,
      "subtitle": "Celebrating Excellence in Precision Manufacturing"
    },
    "certificates": {
      "type": "certificates",
      "items": [
        {
          "id": "iso-quality",
          "name": "ISO 9001:2015",
          "image": "/placeholder.svg",
          "description": "Certified quality management system ensuring consistent product excellence"
        },
        {
          "id": "iso-environmental",
          "name": "ISO 14001:2015",
          "image": "/placeholder.svg",
          "description": "Environmental management certification demonstrating sustainable manufacturing practices"
        }
      ],
      "title": "Certifications & Standards",
      "enabled": true,
      "subtitle": "Committed to Global Quality and Sustainability Standards"
    },
    "companyJourney": {
      "type": "company-journey",
      "items": [
        {
          "year": "2005",
          "title": "Company Foundation",
          "description": "Established with a vision to provide high-precision manufacturing solutions for automotive and pneumatic sectors"
        },
        {
          "year": "2010",
          "title": "First Major Expansion",
          "description": "Expanded manufacturing facilities and introduced advanced CNC machining technologies"
        },
        {
          "year": "2015",
          "title": "ISO Certification Achievement",
          "description": "Obtained ISO 9001:2015 certification, marking a milestone in quality management"
        },
        {
          "year": "2020",
          "title": "Technology Upgrade",
          "description": "Invested in state-of-the-art precision manufacturing equipment and automation technologies"
        }
      ],
      "title": "Our Journey",
      "enabled": true,
      "subtitle": "A Story of Continuous Growth and Innovation"
    },
    "infrastructure": {
      "type": "infrastructure",
      "items": [
        {
          "id": "cnc-machines",
          "image": "https://images.unsplash.com/photo-1581579186913-45ac24ed53d2",
          "title": "Advanced CNC Machining Center",
          "capacity": "20+ High-Precision CNC Machines",
          "description": "Cutting-edge CNC machining capabilities for complex precision component manufacturing",
          "specifications": "Multi-axis precision, tolerance: ±0.01mm"
        }
      ],
      "title": "Our Infrastructure",
      "enabled": true,
      "subtitle": "State-of-the-Art Manufacturing Capabilities"
    },
    "companyOverview": {
      "type": "company-overview",
      "image": "https://images.unsplash.com/photo-1581579186913-45ac24ed53d2",
      "items": [
        {
          "id": "overview",
          "content": "Jyoti Precision is a leading manufacturer of precision components for automotive and pneumatic sectors, established in 2005. We specialize in producing over 100 part types with unparalleled quality and technological innovation.",
          "highlights": [
            "ISO 9001:2015 Certified",
            "Advanced CNC Manufacturing",
            "Pan-India Operations",
            "Custom Engineering Solutions",
            "Rapid Prototyping Capabilities",
            "99.8% On-Time Delivery"
          ]
        }
      ],
      "title": "Company Overview",
      "enabled": true,
      "subtitle": "Precision Engineering, Uncompromising Quality"
    },
    "manufacturingProcess": {
      "type": "manufacturing-process",
      "items": [
        {
          "id": "design",
          "step": 1,
          "title": "Engineering Design",
          "description": "Comprehensive design and engineering analysis using advanced CAD/CAM technologies"
        },
        {
          "id": "material",
          "step": 2,
          "title": "Material Selection",
          "description": "Precision material sourcing focusing on brass and high-performance alloys"
        },
        {
          "id": "production",
          "step": 3,
          "title": "Precision Manufacturing",
          "description": "Advanced CNC machining with highest accuracy and repeatability"
        },
        {
          "id": "quality",
          "step": 4,
          "title": "Quality Assurance",
          "description": "Rigorous multi-stage quality control and dimensional inspection"
        },
        {
          "id": "finishing",
          "step": 5,
          "title": "Surface Treatment",
          "description": "Advanced surface finishing techniques for enhanced component performance"
        },
        {
          "id": "delivery",
          "step": 6,
          "title": "Packaging & Delivery",
          "description": "Secure packaging and timely delivery with comprehensive documentation"
        }
      ],
      "title": "Manufacturing Process",
      "enabled": true,
      "subtitle": "Systematic Approach to Precision Engineering"
    }
  }
}